LICENSE
MANIFEST.in
README.md
pyproject.toml
setup.cfg
setup.py
aim/VERSION
aim/__about__.py
aim/__init__.py
aim/__version__.py
aim/catboost.py
aim/fastai.py
aim/hugging_face.py
aim/keras.py
aim/keras_tuner.py
aim/lightgbm.py
aim/mxnet.py
aim/optuna.py
aim/paddle.py
aim/pytorch.py
aim/pytorch_ignite.py
aim/pytorch_lightning.py
aim/tensorflow.py
aim/xgboost.py
aim/cli/__init__.py
aim/cli/cli.py
aim/cli/configs.py
aim/cli/utils.py
aim/cli/watcher_cli.py
aim/cli/convert/__init__.py
aim/cli/convert/commands.py
aim/cli/convert/processors/__init__.py
aim/cli/convert/processors/mlflow.py
aim/cli/convert/processors/tensorboard.py
aim/cli/convert/processors/wandb.py
aim/cli/init/__init__.py
aim/cli/init/commands.py
aim/cli/manager/__init__.py
aim/cli/manager/manager.py
aim/cli/reindex/__init__.py
aim/cli/reindex/commands.py
aim/cli/runs/__init__.py
aim/cli/runs/commands.py
aim/cli/runs/utils.py
aim/cli/server/__init__.py
aim/cli/server/commands.py
aim/cli/storage/__init__.py
aim/cli/storage/commands.py
aim/cli/up/__init__.py
aim/cli/up/commands.py
aim/cli/up/utils.py
aim/cli/upgrade/__init__.py
aim/cli/upgrade/utils.py
aim/cli/upgrade/_legacy_repo/__init__.py
aim/cli/upgrade/_legacy_repo/configs.py
aim/cli/upgrade/_legacy_repo/metric_artifact.py
aim/cli/upgrade/_legacy_repo/proto/__init__.py
aim/cli/upgrade/_legacy_repo/proto/base_pb2.py
aim/cli/upgrade/_legacy_repo/proto/metric_pb2.py
aim/cli/upgrade/_legacy_repo/repo/__init__.py
aim/cli/upgrade/_legacy_repo/repo/metric.py
aim/cli/upgrade/_legacy_repo/repo/repo.py
aim/cli/upgrade/_legacy_repo/repo/run.py
aim/cli/upgrade/_legacy_repo/repo/trace.py
aim/cli/upgrade/_legacy_repo/repo/utils.py
aim/cli/version/__init__.py
aim/cli/version/commands.py
aim/ext/__init__.py
aim/ext/exception_resistant.py
aim/ext/utils.py
aim/ext/cleanup/__init__.py
aim/ext/notebook/__init__.py
aim/ext/notebook/notebook.py
aim/ext/notifier/__init__.py
aim/ext/notifier/base_notifier.py
aim/ext/notifier/config.py
aim/ext/notifier/config_default.json
aim_with_auth_support.egg-info/PKG-INFO
aim_with_auth_support.egg-info/SOURCES.txt
aim_with_auth_support.egg-info/dependency_links.txt
aim_with_auth_support.egg-info/entry_points.txt
aim_with_auth_support.egg-info/requires.txt
aim_with_auth_support.egg-info/top_level.txt
